README.md
setup.py
pyyz/__init__.py
pyyz/pyyz.py
pyyz.egg-info/PKG-INFO
pyyz.egg-info/SOURCES.txt
pyyz.egg-info/dependency_links.txt
pyyz.egg-info/top_level.txt