Metadata-Version: 2.1
Name: pyyz
Version: 0.0.1
Summary: AI tool for Turkish Text Analysis
Author: Halil Kesmez
License: UNKNOWN
Platform: UNKNOWN
